{
  "updated": "2026-05-05T07:32:22+09:00",
  "todays_call": "ブレント原油が5.47%急騰し$114.09（60日移動平均$93.55を大幅上回る）、WTIも3.09%上昇の$105.09となり、INPEXにとって大幅な上振れ要因となっている。同社の会社前提ブレント$63に対し+$51の水準で、原油感応度±54億円/年/$1を踏まえると年間+2,750億円程度の利益押上げ効果が見込まれる。一方で非鉄金属は調整局面となり、LME銅が1.23%下落の$5.859/lb、金も2.15%下落の$4,530.5/ozとなったことで、住友鉱山には銅価格下落で▲25億円程度、金価格下落で▲80億円程度の減益要因が発生している。原油急騰はENEOSにとってもE&P部門の増益とタイムラグ効果によるプラス、商船三井にはタンカー運賃上昇を通じた追い風となる見通し。",
  "data_used": {
    "commodities": [
      "copper",
      "gold",
      "wti",
      "brent",
      "usdjpy"
    ],
    "high_alerts": 2,
    "medium_alerts": 2
  }
}