{
  "updated": "2026-05-10T07:06:10+09:00",
  "todays_call": "**Today's Call**\n\nLME銅が+1.98%上昇し$6.249/lbと20日移動平均を上回る上昇トレンドを継続、住友鉱山に年間+約50億円の押上げ要因となる。ブレント原油も+1.23%上昇の$101.29/bbl（会社前提$63比+$38.29）でINPEXに年間+約2,100億円の大幅上振れ要因、保守的な会社予想（当期利益3,300億円）の大幅上方修正余地を示唆している。金価格は+0.44%の小幅上昇だが$4,720/ozの高水準を維持し、住友鉱山の副産物利益に年間+約350億円のプラス寄与が継続。原油上昇はタンカー運賃上昇を通じて商船三井にも追い風となる一方、ENEOSは在庫評価益とタイムラグ効果で短期的にはプラス要因となる見込み。",
  "data_used": {
    "commodities": [
      "copper",
      "gold",
      "wti",
      "brent",
      "usdjpy"
    ],
    "high_alerts": 0,
    "medium_alerts": 2
  }
}